bannerutils/__init__.py
bannerutils/bannerutils.py
bannerutils-1.1.1.dist-info/LICENCE
bannerutils-1.1.1.dist-info/METADATA
bannerutils-1.1.1.dist-info/WHEEL
bannerutils-1.1.1.dist-info/entry_points.txt
bannerutils-1.1.1.dist-info/top_level.txt
bannerutils-1.1.1.dist-info/RECORD
