Metadata-Version: 2.2
Name: bannerutils
Version: 1.1.1
Summary: Advanced ASCII Banner Generator.
Home-page: https://github.com/jfrzz/bannerutils
Author: @JfrzxCode
Author-email: jfrzzzzzzz@gmail.com
Classifier: Programming Language :: Python :: 3
Classifier: License :: OSI Approved :: MIT License
Classifier: Operating System :: OS Independent
Requires-Python: >=3.6
License-File: LICENCE
Requires-Dist: pyfiglet
Requires-Dist: pyperclip
Dynamic: author
Dynamic: author-email
Dynamic: classifier
Dynamic: description
Dynamic: description-content-type
Dynamic: home-page
Dynamic: requires-dist
Dynamic: requires-python
Dynamic: summary
